[
    {
        "model": "transmit_elexon.transmit",
        "id": "1",
        "fields": {
            "Date": "2021-08-09",
            "Volume": "598506.0"
        }
    },
    {
        "model": "transmit_elexon.transmit",
        "id": "2",
        "fields": {
            "Date": "2021-08-10",
            "Volume": "606851.0"
        }
    },
    {
        "model": "transmit_elexon.transmit",
        "id": "3",
        "fields": {
            "Date": "2021-08-11",
            "Volume": "606775.0"
        }
    },
    {
        "model": "transmit_elexon.transmit",
        "id": "4",
        "fields": {
            "Date": "2021-08-12",
            "Volume": "599532.0"
        }
    },
    {
        "model": "transmit_elexon.transmit",
        "id": "5",
        "fields": {
            "Date": "2021-08-13",
            "Volume": "567374.0"
        }
    },
    {
        "model": "transmit_elexon.transmit",
        "id": "6",
        "fields": {
            "Date": "2021-08-14",
            "Volume": "539090.0"
        }
    },
    {
        "model": "transmit_elexon.transmit",
        "id": "7",
        "fields": {
            "Date": "2021-08-15",
            "Volume": "540922.0"
        }
    },
    {
        "model": "transmit_elexon.transmit",
        "id": "8",
        "fields": {
            "Date": "2021-08-16",
            "Volume": "598526.0"
        }
    },
    {
        "model": "transmit_elexon.transmit",
        "id": "9",
        "fields": {
            "Date": "2021-08-17",
            "Volume": "626249.0"
        }
    },
    {
        "model": "transmit_elexon.transmit",
        "id": "10",
        "fields": {
            "Date": "2021-08-18",
            "Volume": "624089.0"
        }
    },
    {
        "model": "transmit_elexon.transmit",
        "id": "11",
        "fields": {
            "Date": "2021-08-19",
            "Volume": "649463.0"
        }
    },
    {
        "model": "transmit_elexon.transmit",
        "id": "12",
        "fields": {
            "Date": "2021-08-20",
            "Volume": "644518.0"
        }
    },
    {
        "model": "transmit_elexon.transmit",
        "id": "13",
        "fields": {
            "Date": "2021-08-21",
            "Volume": "596857.0"
        }
    },
    {
        "model": "transmit_elexon.transmit",
        "id": "14",
        "fields": {
            "Date": "2021-08-22",
            "Volume": "568906.0"
        }
    },
    {
        "model": "transmit_elexon.transmit",
        "id": "15",
        "fields": {
            "Date": "2021-08-23",
            "Volume": "634758.0"
        }
    },
    {
        "model": "transmit_elexon.transmit",
        "id": "16",
        "fields": {
            "Date": "2021-08-24",
            "Volume": "634397.0"
        }
    },
    {
        "model": "transmit_elexon.transmit",
        "id": "17",
        "fields": {
            "Date": "2021-08-25",
            "Volume": "641892.0"
        }
    },
    {
        "model": "transmit_elexon.transmit",
        "id": "18",
        "fields": {
            "Date": "2021-08-26",
            "Volume": "624346.0"
        }
    },
    {
        "model": "transmit_elexon.transmit",
        "id": "19",
        "fields": {
            "Date": "2021-08-27",
            "Volume": "627502.0"
        }
    },
    {
        "model": "transmit_elexon.transmit",
        "id": "20",
        "fields": {
            "Date": "2021-08-28",
            "Volume": "556976.0"
        }
    },
    {
        "model": "transmit_elexon.transmit",
        "id": "21",
        "fields": {
            "Date": "2021-08-29",
            "Volume": "540253.0"
        }
    },
    {
        "model": "transmit_elexon.transmit",
        "id": "22",
        "fields": {
            "Date": "2021-08-30",
            "Volume": "578467.0"
        }
    },
    {
        "model": "transmit_elexon.transmit",
        "id": "23",
        "fields": {
            "Date": "2021-08-31",
            "Volume": "636278.0"
        }
    },
    {
        "model": "transmit_elexon.transmit",
        "id": "24",
        "fields": {
            "Date": "2021-09-01",
            "Volume": "650911.0"
        }
    },
    {
        "model": "transmit_elexon.transmit",
        "id": "25",
        "fields": {
            "Date": "2021-09-02",
            "Volume": "653861.0"
        }
    },
    {
        "model": "transmit_elexon.transmit",
        "id": "26",
        "fields": {
            "Date": "2021-09-03",
            "Volume": "644736.0"
        }
    },
    {
        "model": "transmit_elexon.transmit",
        "id": "27",
        "fields": {
            "Date": "2021-09-04",
            "Volume": "580921.0"
        }
    },
    {
        "model": "transmit_elexon.transmit",
        "id": "28",
        "fields": {
            "Date": "2021-09-05",
            "Volume": "559397.0"
        }
    },
    {
        "model": "transmit_elexon.transmit",
        "id": "29",
        "fields": {
            "Date": "2021-09-06",
            "Volume": "647188.0"
        }
    },
    {
        "model": "transmit_elexon.transmit",
        "id": "30",
        "fields": {
            "Date": "2021-09-07",
            "Volume": "643939.0"
        }
    }
]